aiocloud/__init__.py
aiocloud/client.py
aiocloud/errors.py
aiocloud/helpers.py
aiocloud/storage.py
aiocloud-0.0.2.dist-info/LICENCE
aiocloud-0.0.2.dist-info/METADATA
aiocloud-0.0.2.dist-info/WHEEL
aiocloud-0.0.2.dist-info/top_level.txt
aiocloud-0.0.2.dist-info/RECORD
