Metadata-Version: 2.1
Name: aiocloud
Version: 0.0.2
Summary: API wrapper for Soundcloud.
Home-page: https://github.com/Exahilosys/aiocloud
Author: Exahilosys
Author-email: exahilosys@gmail.com
License: MIT
Download-URL: https://github.com/Exahilosys/aiocloud/archive/v0.0.2.tar.gz
Platform: UNKNOWN
Classifier: License :: OSI Approved :: MIT License
Classifier: Intended Audience :: Developers
Classifier: Natural Language :: English
Classifier: Operating System :: OS Independent
Classifier: Programming Language :: Python :: 3.6
Classifier: Topic :: Software Development :: Libraries
Classifier: Topic :: Software Development :: Libraries :: Python Modules
Classifier: Topic :: Utilities
Requires-Dist: aiohttp
Requires-Dist: yarl
